dapiclient/__init__.py
dapiclient/client.py
dapiclient/test-dapi.py
dapiclient/test-dapiclient.py
dapiclient/test-mndiscovery.py
dapiclient/MNDiscovery/__init__.py
dapiclient/MNDiscovery/masternode_discovery.py
dapiclient/MNDiscovery/masternode_list.py
dapiclient/MNDiscovery/masternode_list_provider.py
dapiclient/rpc/__init__.py
dapiclient/rpc/grpc/__init__.py
dapiclient/rpc/grpc/core_pb2.py
dapiclient/rpc/grpc/core_pb2_grpc.py
dapiclient/rpc/grpc/grpc_client.py
dapiclient/rpc/grpc/platform_pb2.py
dapiclient/rpc/grpc/platform_pb2_grpc.py
dapiclient/rpc/jsonrpc/__init__.py
dapiclient/rpc/jsonrpc/jsonrpc_client.py
dapiclient-0.0.7.dist-info/LICENSE
dapiclient-0.0.7.dist-info/METADATA
dapiclient-0.0.7.dist-info/WHEEL
dapiclient-0.0.7.dist-info/top_level.txt
dapiclient-0.0.7.dist-info/RECORD
