Metadata-Version: 2.1
Name: dapiclient
Version: 0.0.7
Summary: A python client SDK for DASH Platform
Home-page: https://github.com/mayoreee/dapi-client-py
Author: mayoreee
Project-URL: Source Code, https://github.com/mayoreee/dapi-client-py
Project-URL: Bug Tracker, https://github.com/mayoreee/dapi-client-py/issues
Classifier: Programming Language :: Python :: 3
Classifier: License :: OSI Approved :: MIT License
Requires-Python: >=3.9
License-File: LICENSE
Requires-Dist: base58 (>='2.1.0')
Requires-Dist: cbor2 (>='5.4.0')
Requires-Dist: certifi (>='2021.5.30')
Requires-Dist: charset-normalizer (>='2.0.3')
Requires-Dist: grpcio (>='1.38.1')
Requires-Dist: idna (>='3.2')
Requires-Dist: protobuf (>='3.17.3')
Requires-Dist: requests (>='2.26.0')
Requires-Dist: six (>='1.16.0')
Requires-Dist: urllib3 (>='1.26.6')
